aiogram_cache/__init__.py
aiogram_cache/middlewares.py
aiogram_cache/storage.py
aiogram_cache/storages/__init__.py
aiogram_cache/storages/memory.py
aiogram_cache/storages/redis.py
aiogram_cache-0.1.dist-info/METADATA
aiogram_cache-0.1.dist-info/WHEEL
aiogram_cache-0.1.dist-info/top_level.txt
aiogram_cache-0.1.dist-info/RECORD
