Metadata-Version: 2.1
Name: aiogram-cache
Version: 0.1
Author: alteralt
Project-URL: Source, https://github.com/alteralt/aiogram_cache
Classifier: Development Status :: 5 - Production/Stable
Classifier: Intended Audience :: Developers
Classifier: Natural Language :: Russian
Classifier: Programming Language :: Python
Classifier: Programming Language :: Python :: 3.7
Classifier: Programming Language :: Python :: 3.8
Classifier: Programming Language :: Python :: 3.9
Requires-Python: >=3.7
Requires-Dist: aiogram (>=2.20)
